atomicguard/__init__.py
atomicguard/application/__init__.py
atomicguard/application/action_pair.py
atomicguard/application/agent.py
atomicguard/application/workflow.py
atomicguard/domain/__init__.py
atomicguard/domain/exceptions.py
atomicguard/domain/interfaces.py
atomicguard/domain/models.py
atomicguard/domain/prompts.py
atomicguard/guards/__init__.py
atomicguard/guards/composite/__init__.py
atomicguard/guards/composite/base.py
atomicguard/guards/dynamic/__init__.py
atomicguard/guards/dynamic/test_runner.py
atomicguard/guards/interactive/__init__.py
atomicguard/guards/interactive/human.py
atomicguard/guards/static/__init__.py
atomicguard/guards/static/imports.py
atomicguard/guards/static/syntax.py
atomicguard/infrastructure/__init__.py
atomicguard/infrastructure/registry.py
atomicguard/infrastructure/llm/__init__.py
atomicguard/infrastructure/llm/huggingface.py
atomicguard/infrastructure/llm/mock.py
atomicguard/infrastructure/llm/ollama.py
atomicguard/infrastructure/persistence/__init__.py
atomicguard/infrastructure/persistence/checkpoint.py
atomicguard/infrastructure/persistence/filesystem.py
atomicguard/infrastructure/persistence/memory.py
atomicguard/schemas/__init__.py
atomicguard-1.2.0.dist-info/licenses/LICENSE
atomicguard-1.2.0.dist-info/METADATA
atomicguard-1.2.0.dist-info/WHEEL
atomicguard-1.2.0.dist-info/entry_points.txt
atomicguard-1.2.0.dist-info/top_level.txt
atomicguard-1.2.0.dist-info/RECORD
