Metadata-Version: 2.4
Name: atomicguard
Version: 1.2.0
Summary: A Dual-State Agent Framework for reliable LLM code generation with guard-validated loops
Author-email: Matthew Thompson <thompsonson@gmail.com>
Maintainer-email: Matthew Thompson <thompsonson@gmail.com>
License: MIT
Project-URL: Homepage, https://github.com/thompsonson/atomicguard
Project-URL: Repository, https://github.com/thompsonson/atomicguard
Project-URL: Documentation, https://github.com/thompsonson/atomicguard#readme
Project-URL: Issues, https://github.com/thompsonson/atomicguard/issues
Project-URL: Changelog, https://github.com/thompsonson/atomicguard/blob/main/CHANGELOG.md
Keywords: llm,agents,code-generation,neuro-symbolic,guards,ai,validation
Classifier: Development Status :: 3 - Alpha
Classifier: Intended Audience :: Developers
Classifier: Intended Audience :: Science/Research
Classifier: License :: OSI Approved :: MIT License
Classifier: Operating System :: OS Independent
Classifier: Programming Language :: Python :: 3
Classifier: Programming Language :: Python :: 3.12
Classifier: Programming Language :: Python :: 3.13
Classifier: Programming Language :: Python :: 3.14
Classifier: Topic :: Scientific/Engineering :: Artificial Intelligence
Classifier: Topic :: Software Development :: Code Generators
Classifier: Typing :: Typed
Requires-Python: >=3.12
License-File: LICENSE
Requires-Dist: matplotlib>=3.10.0
Requires-Dist: openhands-ai>=0.27.0
Requires-Dist: pydantic-ai>=1.0.0
Requires-Dist: pytestarch>=4.0.1
Dynamic: license-file
